exchangerateapi/__init__.py
exchangerateapi/client.py
exchangerateapi_python-0.1.0.dist-info/licenses/LICENSE
exchangerateapi_python-0.1.0.dist-info/METADATA
exchangerateapi_python-0.1.0.dist-info/WHEEL
exchangerateapi_python-0.1.0.dist-info/top_level.txt
exchangerateapi_python-0.1.0.dist-info/RECORD
