Metadata-Version: 2.4
Name: exchangerateapi-python
Version: 0.1.0
Summary: Python wrapper for exchangerateapi.net with latest and historical endpoints
Author: exchangerateapinet
License: MIT
Project-URL: Homepage, https://github.com/exchangerateapinet/exchangerateapi-python
Keywords: exchangerate,currency,forex,api,wrapper
Classifier: Programming Language :: Python :: 3
Classifier: License :: OSI Approved :: MIT License
Classifier: Operating System :: OS Independent
Requires-Python: >=3.8
License-File: LICENSE
Dynamic: license-file
